dtx_models/__init__.py
dtx_models/analysis.py
dtx_models/base.py
dtx_models/campaigns/__init__.py
dtx_models/campaigns/runbooks.py
dtx_models/evaluator.py
dtx_models/exceptions.py
dtx_models/plugins/__init__.py
dtx_models/plugins/xtream/__init__.py
dtx_models/plugins/xtream/config.py
dtx_models/plugins/xtream/plan.py
dtx_models/plugins/xtream/results.py
dtx_models/prompt_canvas/__init__.py
dtx_models/prompt_canvas/attack_strategies/__init__.py
dtx_models/prompt_canvas/attack_strategies/jailbreaks.py
dtx_models/prompt_canvas/base.py
dtx_models/prompt_canvas/behavior.py
dtx_models/prompt_canvas/converter.py
dtx_models/prompt_canvas/prompt_templates/converter_prompts.py
dtx_models/prompt_canvas/scorers/__init__.py
dtx_models/prompt_canvas/scorers/evaluators.py
dtx_models/prompt_canvas/workflows/attack_recipes.py
dtx_models/prompt_canvas/workflows/prompt_converter.py
dtx_models/prompts.py
dtx_models/providers/__init__.py
dtx_models/providers/ai21.py
dtx_models/providers/aleph_alpha.py
dtx_models/providers/anthropic.py
dtx_models/providers/anyscale.py
dtx_models/providers/azure_ai.py
dtx_models/providers/azure_openAI.py
dtx_models/providers/base.py
dtx_models/providers/baseten.py
dtx_models/providers/bedrock_claude.py
dtx_models/providers/cerebras.py
dtx_models/providers/clarifai.py
dtx_models/providers/cloudflare_workers.py
dtx_models/providers/cohere.py
dtx_models/providers/databricks.py
dtx_models/providers/deepgram.py
dtx_models/providers/deepseek.py
dtx_models/providers/elevenlabs.py
dtx_models/providers/featherless_ai.py
dtx_models/providers/fireworks.py
dtx_models/providers/galadriel.py
dtx_models/providers/gemini.py
dtx_models/providers/google_aistudio.py
dtx_models/providers/google_vertex_ai.py
dtx_models/providers/gradio.py
dtx_models/providers/groq.py
dtx_models/providers/hf.py
dtx_models/providers/http.py
dtx_models/providers/ibm_watsonx.py
dtx_models/providers/infinity.py
dtx_models/providers/jina_ai.py
dtx_models/providers/litellm.py
dtx_models-0.47.0.dist-info/METADATA
dtx_models-0.47.0.dist-info/WHEEL
dtx_models-0.47.0.dist-info/RECORD
