Metadata-Version: 2.4
Name: dtx-models
Version: 0.47.0
Summary: Shared model schemas and YAML-based configurations for the DTX framework.
Author: JC
Author-email: jitendra@detoxio.ai
Requires-Python: >=3.10,<4.0
Classifier: Programming Language :: Python :: 3
Classifier: Programming Language :: Python :: 3.10
Classifier: Programming Language :: Python :: 3.11
Classifier: Programming Language :: Python :: 3.12
Classifier: Programming Language :: Python :: 3.13
Classifier: Programming Language :: Python :: 3.14
Requires-Dist: pydantic (>=2.11.5,<3.0.0)
Requires-Dist: pydantic-yaml (>=1.5.1,<2.0.0)
Requires-Dist: pyyaml (>=6.0.2,<7.0.0)
Project-URL: Homepage, https://docs.detoxio.ai
